[
  {
    "ID_GRUPO": 1,
    "ID_LINEA": 445,
    "ID_TRAYECTO": 10,
    "ID_TRAYECTO_SAE": null,
    "DESC_TRAYECTO": "10 ESTACIO-MROIG-ESCOLA FERRAN I CLUA",
    "DESC_REDUCIDA": "LV4.2 Est-MR-EFiC",
    "PRINCIPAL": "S",
    "SENTIDO": "I",
    "INI_TRAYECTO": 495,
    "FIN_TRAYECTO": 1050,
    "ID_TRAYECTO_CONCAT": null,
    "TrayectosDet": [
      {
        "Parada": {
          "DESC_PARADA": "PL ESTACIÓ",
          "COD_PARADA": 1062,
          "ID_GRUPO": 1,
          "ID_PARADA": 19863,
          "ID_MUNICIPIO": 469767,
          "MUNICIPIO": "VALLDOREIX",
          "EXPLOTADORA": "SARBUS",
          "ID_ZONA": 0,
          "ZONA": null,
          "ID_EXPLOTADORA": 1,
          "UTMX": 422254,
          "UTMY": 4590189,
          "LATITUD": 41.457726,
          "LONGITUD": 2.068087,
          "ID_SUBZONA": null,
          "SUBZONA": null,
          "CONCESIONES": null
        },
        "ID_GRUPO": 1,
        "ID_LINEA": 445,
        "ID_TRAYECTO": 10,
        "SECUENCIA": 10,
        "ID_PARADA": 19863,
        "NKM_ORIGEN": 0,
        "SUBE_BAJA": 2
      },
      {
        "Parada": {
          "DESC_PARADA": "PL. SANT JAUME / MENTA",
          "COD_PARADA": 9161,
          "ID_GRUPO": 1,
          "ID_PARADA": 9161,
          "ID_MUNICIPIO": 82055,
          "MUNICIPIO": "SANT CUGAT DEL VALLÈS",
          "EXPLOTADORA": "SARBUS",
          "ID_ZONA": 0,
          "ZONA": null,
          "ID_EXPLOTADORA": 1,
          "UTMX": 422445,
          "UTMY": 4589810,
          "LATITUD": 41.454283615193,
          "LONGITUD": 2.0703165282524,
          "ID_SUBZONA": null,
          "SUBZONA": null,
          "CONCESIONES": null
        },
        "ID_GRUPO": 1,
        "ID_LINEA": 445,
        "ID_TRAYECTO": 10,
        "SECUENCIA": 20,
        "ID_PARADA": 9161,
        "NKM_ORIGEN": 0,
        "SUBE_BAJA": 1
      },
      {
        "Parada": {
          "DESC_PARADA": "PL. DELS ESTRETS",
          "COD_PARADA": 9157,
          "ID_GRUPO": 1,
          "ID_PARADA": 9157,
          "ID_MUNICIPIO": 82055,
          "MUNICIPIO": "SANT CUGAT DEL VALLÈS",
          "EXPLOTADORA": "SARBUS",
          "ID_ZONA": 0,
          "ZONA": null,
          "ID_EXPLOTADORA": 1,
          "UTMX": 422805,
          "UTMY": 4589903,
          "LATITUD": 41.45515595651,
          "LONGITUD": 2.0746143285697,
          "ID_SUBZONA": null,
          "SUBZONA": null,
          "CONCESIONES": null
        },
        "ID_GRUPO": 1,
        "ID_LINEA": 445,
        "ID_TRAYECTO": 10,
        "SECUENCIA": 30,
        "ID_PARADA": 9157,
        "NKM_ORIGEN": 0,
        "SUBE_BAJA": 1
      },
      {
        "Parada": {
          "DESC_PARADA": "CANAL DE LA MÀNEGA (COL·LEGI EL PINAR)",
          "COD_PARADA": 9134,
          "ID_GRUPO": 1,
          "ID_PARADA": 9134,
          "ID_MUNICIPIO": 82055,
          "MUNICIPIO": "SANT CUGAT DEL VALLÈS",
          "EXPLOTADORA": "SARBUS",
          "ID_ZONA": 0,
          "ZONA": null,
          "ID_EXPLOTADORA": 1,
          "UTMX": 422778,
          "UTMY": 4590256,
          "LATITUD": 41.4573,
          "LONGITUD": 2.07383,
          "ID_SUBZONA": null,
          "SUBZONA": null,
          "CONCESIONES": null
        },
        "ID_GRUPO": 1,
        "ID_LINEA": 445,
        "ID_TRAYECTO": 10,
        "SECUENCIA": 40,
        "ID_PARADA": 9134,
        "NKM_ORIGEN": 0,
        "SUBE_BAJA": 1
      },
      {
        "Parada": {
          "DESC_PARADA": "ARNAU CADELL",
          "COD_PARADA": 9159,
          "ID_GRUPO": 1,
          "ID_PARADA": 9159,
          "ID_MUNICIPIO": 82055,
          "MUNICIPIO": "SANT CUGAT DEL VALLÈS",
          "EXPLOTADORA": "SARBUS",
          "ID_ZONA": 0,
          "ZONA": null,
          "ID_EXPLOTADORA": 1,
          "UTMX": 422425,
          "UTMY": 4590360,
          "LATITUD": 41.45923516314,
          "LONGITUD": 2.0700063388967,
          "ID_SUBZONA": null,
          "SUBZONA": null,
          "CONCESIONES": null
        },
        "ID_GRUPO": 1,
        "ID_LINEA": 445,
        "ID_TRAYECTO": 10,
        "SECUENCIA": 50,
        "ID_PARADA": 9159,
        "NKM_ORIGEN": 0,
        "SUBE_BAJA": 1
      },
      {
        "Parada": {
          "DESC_PARADA": "AV. DE VILADELPRAT (ESTACIÓ VALLDOREIX)",
          "COD_PARADA": 9160,
          "ID_GRUPO": 1,
          "ID_PARADA": 9160,
          "ID_MUNICIPIO": 82055,
          "MUNICIPIO": "SANT CUGAT DEL VALLÈS",
          "EXPLOTADORA": "SARBUS",
          "ID_ZONA": 0,
          "ZONA": null,
          "ID_EXPLOTADORA": 1,
          "UTMX": 422301,
          "UTMY": 4590236,
          "LATITUD": 41.458106366352,
          "LONGITUD": 2.0685377541971,
          "ID_SUBZONA": null,
          "SUBZONA": null,
          "CONCESIONES": null
        },
        "ID_GRUPO": 1,
        "ID_LINEA": 445,
        "ID_TRAYECTO": 10,
        "SECUENCIA": 55,
        "ID_PARADA": 9160,
        "NKM_ORIGEN": 0,
        "SUBE_BAJA": 1
      },
      {
        "Parada": {
          "DESC_PARADA": "PL ESTACIÓ",
          "COD_PARADA": 1062,
          "ID_GRUPO": 1,
          "ID_PARADA": 19863,
          "ID_MUNICIPIO": 469767,
          "MUNICIPIO": "VALLDOREIX",
          "EXPLOTADORA": "SARBUS",
          "ID_ZONA": 0,
          "ZONA": null,
          "ID_EXPLOTADORA": 1,
          "UTMX": 422254,
          "UTMY": 4590189,
          "LATITUD": 41.457726,
          "LONGITUD": 2.068087,
          "ID_SUBZONA": null,
          "SUBZONA": null,
          "CONCESIONES": null
        },
        "ID_GRUPO": 1,
        "ID_LINEA": 445,
        "ID_TRAYECTO": 10,
        "SECUENCIA": 60,
        "ID_PARADA": 19863,
        "NKM_ORIGEN": 1,
        "SUBE_BAJA": 3
      }
    ],
    "COLOR": "#FF7839",
    "CIRCULAR": "S",
    "numLinea": "445"
  }
]