[
  {
    "ID_GRUPO": 1,
    "ID_LINEA": 47,
    "ID_TRAYECTO": 4,
    "ID_TRAYECTO_SAE": 101,
    "DESC_TRAYECTO": "(E11.1) MATARÓ - BCN (DISSABTES I FESTIUS)",
    "DESC_REDUCIDA": "MAT-BARNA(SAB-FEST)",
    "PRINCIPAL": "S",
    "SENTIDO": "I",
    "INI_TRAYECTO": 540,
    "FIN_TRAYECTO": 1380,
    "ID_TRAYECTO_CONCAT": null,
    "TrayectosDet": [
      {
        "Parada": {
          "DESC_PARADA": "PL. DE LES TERESES",
          "COD_PARADA": 20,
          "ID_GRUPO": 1,
          "ID_PARADA": 7077,
          "ID_MUNICIPIO": 81213,
          "MUNICIPIO": "MATARÓ",
          "EXPLOTADORA": "CASAS",
          "ID_ZONA": 0,
          "ZONA": null,
          "ID_EXPLOTADORA": 3,
          "UTMX": 453574,
          "UTMY": 4598922,
          "LATITUD": 41.53885529546,
          "LONGITUD": 2.4423067153257,
          "ID_SUBZONA": null,
          "SUBZONA": null,
          "CONCESIONES": null
        },
        "ID_GRUPO": 1,
        "ID_LINEA": 47,
        "ID_TRAYECTO": 4,
        "SECUENCIA": 10,
        "ID_PARADA": 7077,
        "NKM_ORIGEN": 0,
        "SUBE_BAJA": 2
      },
      {
        "Parada": {
          "DESC_PARADA": "C. DE SANT ISIDOR",
          "COD_PARADA": 291,
          "ID_GRUPO": 1,
          "ID_PARADA": 13521,
          "ID_MUNICIPIO": 81213,
          "MUNICIPIO": "MATARÓ",
          "EXPLOTADORA": "CASAS",
          "ID_ZONA": 0,
          "ZONA": null,
          "ID_EXPLOTADORA": 3,
          "UTMX": 453396,
          "UTMY": 4599157,
          "LATITUD": 41.540897242805,
          "LONGITUD": 2.4401502037049,
          "ID_SUBZONA": null,
          "SUBZONA": null,
          "CONCESIONES": null
        },
        "ID_GRUPO": 1,
        "ID_LINEA": 47,
        "ID_TRAYECTO": 4,
        "SECUENCIA": 20,
        "ID_PARADA": 13521,
        "NKM_ORIGEN": 0.32,
        "SUBE_BAJA": 2
      },
      {
        "Parada": {
          "DESC_PARADA": "PL. D´ESPANYA (PARC CENTRAL)",
          "COD_PARADA": 3990,
          "ID_GRUPO": 1,
          "ID_PARADA": 7154,
          "ID_MUNICIPIO": 81213,
          "MUNICIPIO": "MATARÓ",
          "EXPLOTADORA": "CASAS",
          "ID_ZONA": 0,
          "ZONA": null,
          "ID_EXPLOTADORA": 3,
          "UTMX": 453525,
          "UTMY": 4599567,
          "LATITUD": 41.544597689691,
          "LONGITUD": 2.4416693344182,
          "ID_SUBZONA": null,
          "SUBZONA": null,
          "CONCESIONES": null
        },
        "ID_GRUPO": 1,
        "ID_LINEA": 47,
        "ID_TRAYECTO": 4,
        "SECUENCIA": 30,
        "ID_PARADA": 7154,
        "NKM_ORIGEN": 0.9,
        "SUBE_BAJA": 2
      },
      {
        "Parada": {
          "DESC_PARADA": "CAMÍ DE LA GEGANTA/PL. GRANOLLERS (POLICIA LOCAL)",
          "COD_PARADA": 7475,
          "ID_GRUPO": 1,
          "ID_PARADA": 21749,
          "ID_MUNICIPIO": 81213,
          "MUNICIPIO": "MATARÓ",
          "EXPLOTADORA": "CASAS",
          "ID_ZONA": 0,
          "ZONA": null,
          "ID_EXPLOTADORA": 3,
          "UTMX": 453090,
          "UTMY": 4599200,
          "LATITUD": 41.541266,
          "LONGITUD": 2.436482,
          "ID_SUBZONA": null,
          "SUBZONA": null,
          "CONCESIONES": null
        },
        "ID_GRUPO": 1,
        "ID_LINEA": 47,
        "ID_TRAYECTO": 4,
        "SECUENCIA": 45,
        "ID_PARADA": 21749,
        "NKM_ORIGEN": 1.457,
        "SUBE_BAJA": 2
      },
      {
        "Parada": {
          "DESC_PARADA": "RDA. DE LA REPÚBLICA / C. DE MIQUEL BIADA",
          "COD_PARADA": 30,
          "ID_GRUPO": 1,
          "ID_PARADA": 7048,
          "ID_MUNICIPIO": 81213,
          "MUNICIPIO": "MATARÓ",
          "EXPLOTADORA": "CASAS",
          "ID_ZONA": 0,
          "ZONA": null,
          "ID_EXPLOTADORA": 3,
          "UTMX": 453111,
          "UTMY": 4598733,
          "LATITUD": 41.537061683521,
          "LONGITUD": 2.4367710552247,
          "ID_SUBZONA": null,
          "SUBZONA": null,
          "CONCESIONES": null
        },
        "ID_GRUPO": 1,
        "ID_LINEA": 47,
        "ID_TRAYECTO": 4,
        "SECUENCIA": 50,
        "ID_PARADA": 7048,
        "NKM_ORIGEN": 2.2,
        "SUBE_BAJA": 2
      },
      {
        "Parada": {
          "DESC_PARADA": "CAMÍ RAL/C. PIZARRO (PL. DR. FLEMING)",
          "COD_PARADA": 11,
          "ID_GRUPO": 1,
          "ID_PARADA": 7159,
          "ID_MUNICIPIO": 81213,
          "MUNICIPIO": "MATARÓ",
          "EXPLOTADORA": "CASAS",
          "ID_ZONA": 0,
          "ZONA": null,
          "ID_EXPLOTADORA": 3,
          "UTMX": 453353,
          "UTMY": 4598354,
          "LATITUD": 41.533662215034,
          "LONGITUD": 2.4397015280912,
          "ID_SUBZONA": null,
          "SUBZONA": null,
          "CONCESIONES": null
        },
        "ID_GRUPO": 1,
        "ID_LINEA": 47,
        "ID_TRAYECTO": 4,
        "SECUENCIA": 60,
        "ID_PARADA": 7159,
        "NKM_ORIGEN": 2.7,
        "SUBE_BAJA": 2
      },
      {
        "Parada": {
          "DESC_PARADA": "CAMÍ RAL (PORTA LAIETANA-TECNOCAMPUS)",
          "COD_PARADA": 12,
          "ID_GRUPO": 1,
          "ID_PARADA": 7160,
          "ID_MUNICIPIO": 81213,
          "MUNICIPIO": "MATARÓ",
          "EXPLOTADORA": "CASAS",
          "ID_ZONA": 0,
          "ZONA": null,
          "ID_EXPLOTADORA": 3,
          "UTMX": 453028,
          "UTMY": 4597998,
          "LATITUD": 41.530436687756,
          "LONGITUD": 2.4358336078779,
          "ID_SUBZONA": null,
          "SUBZONA": null,
          "CONCESIONES": null
        },
        "ID_GRUPO": 1,
        "ID_LINEA": 47,
        "ID_TRAYECTO": 4,
        "SECUENCIA": 70,
        "ID_PARADA": 7160,
        "NKM_ORIGEN": 3.2,
        "SUBE_BAJA": 2
      },
      {
        "Parada": {
          "DESC_PARADA": "PL.TETUAN (GVCC /NÀPOLS)",
          "COD_PARADA": 13,
          "ID_GRUPO": 1,
          "ID_PARADA": 7506,
          "ID_MUNICIPIO": 439863,
          "MUNICIPIO": "BARCELONA",
          "EXPLOTADORA": "CASAS",
          "ID_ZONA": 0,
          "ZONA": null,
          "ID_EXPLOTADORA": 3,
          "UTMX": 431313,
          "UTMY": 4583281,
          "LATITUD": 41.39621,
          "LONGITUD": 2.17692,
          "ID_SUBZONA": null,
          "SUBZONA": null,
          "CONCESIONES": null
        },
        "ID_GRUPO": 1,
        "ID_LINEA": 47,
        "ID_TRAYECTO": 4,
        "SECUENCIA": 80,
        "ID_PARADA": 7506,
        "NKM_ORIGEN": 31.84,
        "SUBE_BAJA": 3
      },
      {
        "Parada": {
          "DESC_PARADA": "RONDA DE LA UNIVERSITAT 25",
          "COD_PARADA": 6190,
          "ID_GRUPO": 1,
          "ID_PARADA": 7022,
          "ID_MUNICIPIO": 439863,
          "MUNICIPIO": "BARCELONA",
          "EXPLOTADORA": "CASAS",
          "ID_ZONA": 0,
          "ZONA": null,
          "ID_EXPLOTADORA": 3,
          "UTMX": 430638,
          "UTMY": 4582238,
          "LATITUD": 41.38689,
          "LONGITUD": 2.166885,
          "ID_SUBZONA": null,
          "SUBZONA": null,
          "CONCESIONES": null
        },
        "ID_GRUPO": 1,
        "ID_LINEA": 47,
        "ID_TRAYECTO": 4,
        "SECUENCIA": 90,
        "ID_PARADA": 7022,
        "NKM_ORIGEN": 34.5,
        "SUBE_BAJA": 3
      }
    ],
    "COLOR": "#0BBC90",
    "numLinea": "47"
  },
  {
    "ID_GRUPO": 1,
    "ID_LINEA": 47,
    "ID_TRAYECTO": 2,
    "ID_TRAYECTO_SAE": 2,
    "DESC_TRAYECTO": "(E11.1) BARCELONA - MATARÓ (CENTRE)",
    "DESC_REDUCIDA": "BCN - MAT(CENTRE)",
    "PRINCIPAL": "S",
    "SENTIDO": "V",
    "INI_TRAYECTO": 620,
    "FIN_TRAYECTO": 1260,
    "ID_TRAYECTO_CONCAT": null,
    "TrayectosDet": [
      {
        "Parada": {
          "DESC_PARADA": "RONDA DE LA UNIVERSITAT 25",
          "COD_PARADA": 6190,
          "ID_GRUPO": 1,
          "ID_PARADA": 7022,
          "ID_MUNICIPIO": 439863,
          "MUNICIPIO": "BARCELONA",
          "EXPLOTADORA": "CASAS",
          "ID_ZONA": 0,
          "ZONA": null,
          "ID_EXPLOTADORA": 3,
          "UTMX": 430638,
          "UTMY": 4582238,
          "LATITUD": 41.38689,
          "LONGITUD": 2.166885,
          "ID_SUBZONA": null,
          "SUBZONA": null,
          "CONCESIONES": null
        },
        "ID_GRUPO": 1,
        "ID_LINEA": 47,
        "ID_TRAYECTO": 2,
        "SECUENCIA": 10,
        "ID_PARADA": 7022,
        "NKM_ORIGEN": 0,
        "SUBE_BAJA": 2
      },
      {
        "Parada": {
          "DESC_PARADA": "PL. DE TETUAN",
          "COD_PARADA": 3220,
          "ID_GRUPO": 1,
          "ID_PARADA": 7508,
          "ID_MUNICIPIO": 439863,
          "MUNICIPIO": "BARCELONA",
          "EXPLOTADORA": "CASAS",
          "ID_ZONA": 0,
          "ZONA": null,
          "ID_EXPLOTADORA": 3,
          "UTMX": 431237,
          "UTMY": 4583153,
          "LATITUD": 41.395156051867,
          "LONGITUD": 2.1763409160586,
          "ID_SUBZONA": null,
          "SUBZONA": null,
          "CONCESIONES": null
        },
        "ID_GRUPO": 1,
        "ID_LINEA": 47,
        "ID_TRAYECTO": 2,
        "SECUENCIA": 20,
        "ID_PARADA": 7508,
        "NKM_ORIGEN": 1.305,
        "SUBE_BAJA": 2
      },
      {
        "Parada": {
          "DESC_PARADA": "C. DE LA BOBINADORA (POL. IND. LES HORTES)",
          "COD_PARADA": 5982,
          "ID_GRUPO": 1,
          "ID_PARADA": 7216,
          "ID_MUNICIPIO": 81213,
          "MUNICIPIO": "MATARÓ",
          "EXPLOTADORA": "CASAS",
          "ID_ZONA": 0,
          "ZONA": null,
          "ID_EXPLOTADORA": 3,
          "UTMX": 452540,
          "UTMY": 4597864,
          "LATITUD": 41.5292009102,
          "LONGITUD": 2.4299948328534,
          "ID_SUBZONA": null,
          "SUBZONA": null,
          "CONCESIONES": null
        },
        "ID_GRUPO": 1,
        "ID_LINEA": 47,
        "ID_TRAYECTO": 2,
        "SECUENCIA": 25,
        "ID_PARADA": 7216,
        "NKM_ORIGEN": 28.846,
        "SUBE_BAJA": 3
      },
      {
        "Parada": {
          "DESC_PARADA": "CAMÍ RAL (PORTA LAIETANA-TECNOCAMPUS)",
          "COD_PARADA": 3630,
          "ID_GRUPO": 1,
          "ID_PARADA": 7217,
          "ID_MUNICIPIO": 81213,
          "MUNICIPIO": "MATARÓ",
          "EXPLOTADORA": "CASAS",
          "ID_ZONA": 0,
          "ZONA": null,
          "ID_EXPLOTADORA": 3,
          "UTMX": 453062,
          "UTMY": 4598016,
          "LATITUD": 41.530600811799,
          "LONGITUD": 2.4362397386589,
          "ID_SUBZONA": null,
          "SUBZONA": null,
          "CONCESIONES": null
        },
        "ID_GRUPO": 1,
        "ID_LINEA": 47,
        "ID_TRAYECTO": 2,
        "SECUENCIA": 30,
        "ID_PARADA": 7217,
        "NKM_ORIGEN": 29.515,
        "SUBE_BAJA": 3
      },
      {
        "Parada": {
          "DESC_PARADA": "RDA. DE LA REPÚBLICA / CAMÍ RAL",
          "COD_PARADA": 3620,
          "ID_GRUPO": 1,
          "ID_PARADA": 7218,
          "ID_MUNICIPIO": 81213,
          "MUNICIPIO": "MATARÓ",
          "EXPLOTADORA": "CASAS",
          "ID_ZONA": 0,
          "ZONA": null,
          "ID_EXPLOTADORA": 3,
          "UTMX": 453389,
          "UTMY": 4598445,
          "LATITUD": 41.534483951017,
          "LONGITUD": 2.4401259931173,
          "ID_SUBZONA": null,
          "SUBZONA": null,
          "CONCESIONES": null
        },
        "ID_GRUPO": 1,
        "ID_LINEA": 47,
        "ID_TRAYECTO": 2,
        "SECUENCIA": 40,
        "ID_PARADA": 7218,
        "NKM_ORIGEN": 30.482,
        "SUBE_BAJA": 3
      },
      {
        "Parada": {
          "DESC_PARADA": "RDA. DE LA REPÚBLICA / C. DE MIQUEL BIADA",
          "COD_PARADA": 4825,
          "ID_GRUPO": 1,
          "ID_PARADA": 7219,
          "ID_MUNICIPIO": 81213,
          "MUNICIPIO": "MATARÓ",
          "EXPLOTADORA": "CASAS",
          "ID_ZONA": 0,
          "ZONA": null,
          "ID_EXPLOTADORA": 3,
          "UTMX": 453122,
          "UTMY": 4598737,
          "LATITUD": 41.5371,
          "LONGITUD": 2.4369,
          "ID_SUBZONA": null,
          "SUBZONA": null,
          "CONCESIONES": null
        },
        "ID_GRUPO": 1,
        "ID_LINEA": 47,
        "ID_TRAYECTO": 2,
        "SECUENCIA": 50,
        "ID_PARADA": 7219,
        "NKM_ORIGEN": 30.875,
        "SUBE_BAJA": 3
      },
      {
        "Parada": {
          "DESC_PARADA": "PL. DE LES TERESES",
          "COD_PARADA": 20,
          "ID_GRUPO": 1,
          "ID_PARADA": 7077,
          "ID_MUNICIPIO": 81213,
          "MUNICIPIO": "MATARÓ",
          "EXPLOTADORA": "CASAS",
          "ID_ZONA": 0,
          "ZONA": null,
          "ID_EXPLOTADORA": 3,
          "UTMX": 453574,
          "UTMY": 4598922,
          "LATITUD": 41.53885529546,
          "LONGITUD": 2.4423067153257,
          "ID_SUBZONA": null,
          "SUBZONA": null,
          "CONCESIONES": null
        },
        "ID_GRUPO": 1,
        "ID_LINEA": 47,
        "ID_TRAYECTO": 2,
        "SECUENCIA": 60,
        "ID_PARADA": 7077,
        "NKM_ORIGEN": 31.573,
        "SUBE_BAJA": 3
      }
    ],
    "COLOR": "#0BBC90",
    "numLinea": "47"
  },
  {
    "ID_GRUPO": 1,
    "ID_LINEA": 47,
    "ID_TRAYECTO": 302,
    "ID_TRAYECTO_SAE": 302,
    "DESC_TRAYECTO": "(E11.1) POL.LÍGON LES HORTES - PL. LES TERESES",
    "DESC_REDUCIDA": "P.LES HORTES-PL.TER.",
    "PRINCIPAL": "N",
    "SENTIDO": "V",
    "INI_TRAYECTO": 890,
    "FIN_TRAYECTO": 1320,
    "ID_TRAYECTO_CONCAT": null,
    "TrayectosDet": [
      {
        "Parada": {
          "DESC_PARADA": "C. DE LA BOBINADORA (POL. IND. LES HORTES)",
          "COD_PARADA": 5982,
          "ID_GRUPO": 1,
          "ID_PARADA": 7216,
          "ID_MUNICIPIO": 81213,
          "MUNICIPIO": "MATARÓ",
          "EXPLOTADORA": "CASAS",
          "ID_ZONA": 0,
          "ZONA": null,
          "ID_EXPLOTADORA": 3,
          "UTMX": 452540,
          "UTMY": 4597864,
          "LATITUD": 41.5292009102,
          "LONGITUD": 2.4299948328534,
          "ID_SUBZONA": null,
          "SUBZONA": null,
          "CONCESIONES": null
        },
        "ID_GRUPO": 1,
        "ID_LINEA": 47,
        "ID_TRAYECTO": 302,
        "SECUENCIA": 10,
        "ID_PARADA": 7216,
        "NKM_ORIGEN": 0,
        "SUBE_BAJA": 3
      },
      {
        "Parada": {
          "DESC_PARADA": "CAMÍ RAL (PORTA LAIETANA-TECNOCAMPUS)",
          "COD_PARADA": 3630,
          "ID_GRUPO": 1,
          "ID_PARADA": 7217,
          "ID_MUNICIPIO": 81213,
          "MUNICIPIO": "MATARÓ",
          "EXPLOTADORA": "CASAS",
          "ID_ZONA": 0,
          "ZONA": null,
          "ID_EXPLOTADORA": 3,
          "UTMX": 453062,
          "UTMY": 4598016,
          "LATITUD": 41.530600811799,
          "LONGITUD": 2.4362397386589,
          "ID_SUBZONA": null,
          "SUBZONA": null,
          "CONCESIONES": null
        },
        "ID_GRUPO": 1,
        "ID_LINEA": 47,
        "ID_TRAYECTO": 302,
        "SECUENCIA": 20,
        "ID_PARADA": 7217,
        "NKM_ORIGEN": 0.7,
        "SUBE_BAJA": 3
      },
      {
        "Parada": {
          "DESC_PARADA": "RDA. DE LA REPÚBLICA / CAMÍ RAL",
          "COD_PARADA": 3620,
          "ID_GRUPO": 1,
          "ID_PARADA": 7218,
          "ID_MUNICIPIO": 81213,
          "MUNICIPIO": "MATARÓ",
          "EXPLOTADORA": "CASAS",
          "ID_ZONA": 0,
          "ZONA": null,
          "ID_EXPLOTADORA": 3,
          "UTMX": 453389,
          "UTMY": 4598445,
          "LATITUD": 41.534483951017,
          "LONGITUD": 2.4401259931173,
          "ID_SUBZONA": null,
          "SUBZONA": null,
          "CONCESIONES": null
        },
        "ID_GRUPO": 1,
        "ID_LINEA": 47,
        "ID_TRAYECTO": 302,
        "SECUENCIA": 30,
        "ID_PARADA": 7218,
        "NKM_ORIGEN": 1.3,
        "SUBE_BAJA": 3
      },
      {
        "Parada": {
          "DESC_PARADA": "RDA. DE LA REPÚBLICA / C. DE MIQUEL BIADA",
          "COD_PARADA": 4825,
          "ID_GRUPO": 1,
          "ID_PARADA": 7219,
          "ID_MUNICIPIO": 81213,
          "MUNICIPIO": "MATARÓ",
          "EXPLOTADORA": "CASAS",
          "ID_ZONA": 0,
          "ZONA": null,
          "ID_EXPLOTADORA": 3,
          "UTMX": 453122,
          "UTMY": 4598737,
          "LATITUD": 41.5371,
          "LONGITUD": 2.4369,
          "ID_SUBZONA": null,
          "SUBZONA": null,
          "CONCESIONES": null
        },
        "ID_GRUPO": 1,
        "ID_LINEA": 47,
        "ID_TRAYECTO": 302,
        "SECUENCIA": 40,
        "ID_PARADA": 7219,
        "NKM_ORIGEN": 1.7,
        "SUBE_BAJA": 3
      },
      {
        "Parada": {
          "DESC_PARADA": "PL. DE LES TERESES",
          "COD_PARADA": 20,
          "ID_GRUPO": 1,
          "ID_PARADA": 7077,
          "ID_MUNICIPIO": 81213,
          "MUNICIPIO": "MATARÓ",
          "EXPLOTADORA": "CASAS",
          "ID_ZONA": 0,
          "ZONA": null,
          "ID_EXPLOTADORA": 3,
          "UTMX": 453574,
          "UTMY": 4598922,
          "LATITUD": 41.53885529546,
          "LONGITUD": 2.4423067153257,
          "ID_SUBZONA": null,
          "SUBZONA": null,
          "CONCESIONES": null
        },
        "ID_GRUPO": 1,
        "ID_LINEA": 47,
        "ID_TRAYECTO": 302,
        "SECUENCIA": 50,
        "ID_PARADA": 7077,
        "NKM_ORIGEN": 2.3,
        "SUBE_BAJA": 3
      }
    ],
    "COLOR": "#0BBC90",
    "numLinea": "47"
  },
  {
    "ID_GRUPO": 1,
    "ID_LINEA": 47,
    "ID_TRAYECTO": 7,
    "ID_TRAYECTO_SAE": 402,
    "DESC_TRAYECTO": "(E11.1) BCN - PL GRANOLLERS (DISSABTES+FESTIUS)",
    "DESC_REDUCIDA": "BARNA-P.GR(SAB-FES)",
    "PRINCIPAL": "N",
    "SENTIDO": "V",
    "INI_TRAYECTO": 1320,
    "FIN_TRAYECTO": 1430,
    "ID_TRAYECTO_CONCAT": null,
    "TrayectosDet": [
      {
        "Parada": {
          "DESC_PARADA": "RONDA DE LA UNIVERSITAT 25",
          "COD_PARADA": 6190,
          "ID_GRUPO": 1,
          "ID_PARADA": 7022,
          "ID_MUNICIPIO": 439863,
          "MUNICIPIO": "BARCELONA",
          "EXPLOTADORA": "CASAS",
          "ID_ZONA": 0,
          "ZONA": null,
          "ID_EXPLOTADORA": 3,
          "UTMX": 430638,
          "UTMY": 4582238,
          "LATITUD": 41.38689,
          "LONGITUD": 2.166885,
          "ID_SUBZONA": null,
          "SUBZONA": null,
          "CONCESIONES": null
        },
        "ID_GRUPO": 1,
        "ID_LINEA": 47,
        "ID_TRAYECTO": 7,
        "SECUENCIA": 10,
        "ID_PARADA": 7022,
        "NKM_ORIGEN": 0,
        "SUBE_BAJA": 2
      },
      {
        "Parada": {
          "DESC_PARADA": "PL. DE TETUAN",
          "COD_PARADA": 3220,
          "ID_GRUPO": 1,
          "ID_PARADA": 7508,
          "ID_MUNICIPIO": 439863,
          "MUNICIPIO": "BARCELONA",
          "EXPLOTADORA": "CASAS",
          "ID_ZONA": 0,
          "ZONA": null,
          "ID_EXPLOTADORA": 3,
          "UTMX": 431237,
          "UTMY": 4583153,
          "LATITUD": 41.395156051867,
          "LONGITUD": 2.1763409160586,
          "ID_SUBZONA": null,
          "SUBZONA": null,
          "CONCESIONES": null
        },
        "ID_GRUPO": 1,
        "ID_LINEA": 47,
        "ID_TRAYECTO": 7,
        "SECUENCIA": 20,
        "ID_PARADA": 7508,
        "NKM_ORIGEN": 1.705,
        "SUBE_BAJA": 2
      },
      {
        "Parada": {
          "DESC_PARADA": "C. DE LA BOBINADORA (POL. IND. LES HORTES)",
          "COD_PARADA": 5982,
          "ID_GRUPO": 1,
          "ID_PARADA": 7216,
          "ID_MUNICIPIO": 81213,
          "MUNICIPIO": "MATARÓ",
          "EXPLOTADORA": "CASAS",
          "ID_ZONA": 0,
          "ZONA": null,
          "ID_EXPLOTADORA": 3,
          "UTMX": 452540,
          "UTMY": 4597864,
          "LATITUD": 41.5292009102,
          "LONGITUD": 2.4299948328534,
          "ID_SUBZONA": null,
          "SUBZONA": null,
          "CONCESIONES": null
        },
        "ID_GRUPO": 1,
        "ID_LINEA": 47,
        "ID_TRAYECTO": 7,
        "SECUENCIA": 25,
        "ID_PARADA": 7216,
        "NKM_ORIGEN": 29.246,
        "SUBE_BAJA": 3
      },
      {
        "Parada": {
          "DESC_PARADA": "CAMÍ RAL (PORTA LAIETANA-TECNOCAMPUS)",
          "COD_PARADA": 3630,
          "ID_GRUPO": 1,
          "ID_PARADA": 7217,
          "ID_MUNICIPIO": 81213,
          "MUNICIPIO": "MATARÓ",
          "EXPLOTADORA": "CASAS",
          "ID_ZONA": 0,
          "ZONA": null,
          "ID_EXPLOTADORA": 3,
          "UTMX": 453062,
          "UTMY": 4598016,
          "LATITUD": 41.530600811799,
          "LONGITUD": 2.4362397386589,
          "ID_SUBZONA": null,
          "SUBZONA": null,
          "CONCESIONES": null
        },
        "ID_GRUPO": 1,
        "ID_LINEA": 47,
        "ID_TRAYECTO": 7,
        "SECUENCIA": 30,
        "ID_PARADA": 7217,
        "NKM_ORIGEN": 29.915,
        "SUBE_BAJA": 3
      },
      {
        "Parada": {
          "DESC_PARADA": "RDA. DE LA REPÚBLICA / CAMÍ RAL",
          "COD_PARADA": 3620,
          "ID_GRUPO": 1,
          "ID_PARADA": 7218,
          "ID_MUNICIPIO": 81213,
          "MUNICIPIO": "MATARÓ",
          "EXPLOTADORA": "CASAS",
          "ID_ZONA": 0,
          "ZONA": null,
          "ID_EXPLOTADORA": 3,
          "UTMX": 453389,
          "UTMY": 4598445,
          "LATITUD": 41.534483951017,
          "LONGITUD": 2.4401259931173,
          "ID_SUBZONA": null,
          "SUBZONA": null,
          "CONCESIONES": null
        },
        "ID_GRUPO": 1,
        "ID_LINEA": 47,
        "ID_TRAYECTO": 7,
        "SECUENCIA": 40,
        "ID_PARADA": 7218,
        "NKM_ORIGEN": 30.482,
        "SUBE_BAJA": 3
      },
      {
        "Parada": {
          "DESC_PARADA": "RDA. DE LA REPÚBLICA / C. DE MIQUEL BIADA",
          "COD_PARADA": 4825,
          "ID_GRUPO": 1,
          "ID_PARADA": 7219,
          "ID_MUNICIPIO": 81213,
          "MUNICIPIO": "MATARÓ",
          "EXPLOTADORA": "CASAS",
          "ID_ZONA": 0,
          "ZONA": null,
          "ID_EXPLOTADORA": 3,
          "UTMX": 453122,
          "UTMY": 4598737,
          "LATITUD": 41.5371,
          "LONGITUD": 2.4369,
          "ID_SUBZONA": null,
          "SUBZONA": null,
          "CONCESIONES": null
        },
        "ID_GRUPO": 1,
        "ID_LINEA": 47,
        "ID_TRAYECTO": 7,
        "SECUENCIA": 50,
        "ID_PARADA": 7219,
        "NKM_ORIGEN": 30.875,
        "SUBE_BAJA": 3
      },
      {
        "Parada": {
          "DESC_PARADA": "PL. DE LES TERESES",
          "COD_PARADA": 20,
          "ID_GRUPO": 1,
          "ID_PARADA": 7077,
          "ID_MUNICIPIO": 81213,
          "MUNICIPIO": "MATARÓ",
          "EXPLOTADORA": "CASAS",
          "ID_ZONA": 0,
          "ZONA": null,
          "ID_EXPLOTADORA": 3,
          "UTMX": 453574,
          "UTMY": 4598922,
          "LATITUD": 41.53885529546,
          "LONGITUD": 2.4423067153257,
          "ID_SUBZONA": null,
          "SUBZONA": null,
          "CONCESIONES": null
        },
        "ID_GRUPO": 1,
        "ID_LINEA": 47,
        "ID_TRAYECTO": 7,
        "SECUENCIA": 60,
        "ID_PARADA": 7077,
        "NKM_ORIGEN": 31.573,
        "SUBE_BAJA": 3
      },
      {
        "Parada": {
          "DESC_PARADA": "C. DE SANT ISIDOR",
          "COD_PARADA": 291,
          "ID_GRUPO": 1,
          "ID_PARADA": 13521,
          "ID_MUNICIPIO": 81213,
          "MUNICIPIO": "MATARÓ",
          "EXPLOTADORA": "CASAS",
          "ID_ZONA": 0,
          "ZONA": null,
          "ID_EXPLOTADORA": 3,
          "UTMX": 453396,
          "UTMY": 4599157,
          "LATITUD": 41.540897242805,
          "LONGITUD": 2.4401502037049,
          "ID_SUBZONA": null,
          "SUBZONA": null,
          "CONCESIONES": null
        },
        "ID_GRUPO": 1,
        "ID_LINEA": 47,
        "ID_TRAYECTO": 7,
        "SECUENCIA": 70,
        "ID_PARADA": 13521,
        "NKM_ORIGEN": 31.895,
        "SUBE_BAJA": 3
      },
      {
        "Parada": {
          "DESC_PARADA": "PL. D´ESPANYA (PARC CENTRAL)",
          "COD_PARADA": 3990,
          "ID_GRUPO": 1,
          "ID_PARADA": 7154,
          "ID_MUNICIPIO": 81213,
          "MUNICIPIO": "MATARÓ",
          "EXPLOTADORA": "CASAS",
          "ID_ZONA": 0,
          "ZONA": null,
          "ID_EXPLOTADORA": 3,
          "UTMX": 453525,
          "UTMY": 4599567,
          "LATITUD": 41.544597689691,
          "LONGITUD": 2.4416693344182,
          "ID_SUBZONA": null,
          "SUBZONA": null,
          "CONCESIONES": null
        },
        "ID_GRUPO": 1,
        "ID_LINEA": 47,
        "ID_TRAYECTO": 7,
        "SECUENCIA": 80,
        "ID_PARADA": 7154,
        "NKM_ORIGEN": 32.473,
        "SUBE_BAJA": 3
      },
      {
        "Parada": {
          "DESC_PARADA": "CAMÍ DE LA GEGANTA/PL. GRANOLLERS (POLICIA LOCAL)",
          "COD_PARADA": 7475,
          "ID_GRUPO": 1,
          "ID_PARADA": 21749,
          "ID_MUNICIPIO": 81213,
          "MUNICIPIO": "MATARÓ",
          "EXPLOTADORA": "CASAS",
          "ID_ZONA": 0,
          "ZONA": null,
          "ID_EXPLOTADORA": 3,
          "UTMX": 453090,
          "UTMY": 4599200,
          "LATITUD": 41.541266,
          "LONGITUD": 2.436482,
          "ID_SUBZONA": null,
          "SUBZONA": null,
          "CONCESIONES": null
        },
        "ID_GRUPO": 1,
        "ID_LINEA": 47,
        "ID_TRAYECTO": 7,
        "SECUENCIA": 95,
        "ID_PARADA": 21749,
        "NKM_ORIGEN": 33.73,
        "SUBE_BAJA": 3
      }
    ],
    "COLOR": "#0BBC90",
    "numLinea": "47"
  },
  {
    "ID_GRUPO": 1,
    "ID_LINEA": 47,
    "ID_TRAYECTO": 202,
    "ID_TRAYECTO_SAE": 202,
    "DESC_TRAYECTO": "(E11.1) BCN - POL.LÍGON LES HORTES (RELLEU)",
    "DESC_REDUCIDA": "BARNA-LES HORTES(R)",
    "PRINCIPAL": "N",
    "SENTIDO": "V",
    "INI_TRAYECTO": 860,
    "FIN_TRAYECTO": 1310,
    "ID_TRAYECTO_CONCAT": null,
    "TrayectosDet": [
      {
        "Parada": {
          "DESC_PARADA": "RONDA DE LA UNIVERSITAT 25",
          "COD_PARADA": 6190,
          "ID_GRUPO": 1,
          "ID_PARADA": 7022,
          "ID_MUNICIPIO": 439863,
          "MUNICIPIO": "BARCELONA",
          "EXPLOTADORA": "CASAS",
          "ID_ZONA": 0,
          "ZONA": null,
          "ID_EXPLOTADORA": 3,
          "UTMX": 430638,
          "UTMY": 4582238,
          "LATITUD": 41.38689,
          "LONGITUD": 2.166885,
          "ID_SUBZONA": null,
          "SUBZONA": null,
          "CONCESIONES": null
        },
        "ID_GRUPO": 1,
        "ID_LINEA": 47,
        "ID_TRAYECTO": 202,
        "SECUENCIA": 10,
        "ID_PARADA": 7022,
        "NKM_ORIGEN": 0,
        "SUBE_BAJA": 2
      },
      {
        "Parada": {
          "DESC_PARADA": "PL. DE TETUAN",
          "COD_PARADA": 3220,
          "ID_GRUPO": 1,
          "ID_PARADA": 7508,
          "ID_MUNICIPIO": 439863,
          "MUNICIPIO": "BARCELONA",
          "EXPLOTADORA": "CASAS",
          "ID_ZONA": 0,
          "ZONA": null,
          "ID_EXPLOTADORA": 3,
          "UTMX": 431237,
          "UTMY": 4583153,
          "LATITUD": 41.395156051867,
          "LONGITUD": 2.1763409160586,
          "ID_SUBZONA": null,
          "SUBZONA": null,
          "CONCESIONES": null
        },
        "ID_GRUPO": 1,
        "ID_LINEA": 47,
        "ID_TRAYECTO": 202,
        "SECUENCIA": 20,
        "ID_PARADA": 7508,
        "NKM_ORIGEN": 1.705,
        "SUBE_BAJA": 2
      },
      {
        "Parada": {
          "DESC_PARADA": "C. DE LA BOBINADORA (POL. IND. LES HORTES)",
          "COD_PARADA": 5982,
          "ID_GRUPO": 1,
          "ID_PARADA": 7216,
          "ID_MUNICIPIO": 81213,
          "MUNICIPIO": "MATARÓ",
          "EXPLOTADORA": "CASAS",
          "ID_ZONA": 0,
          "ZONA": null,
          "ID_EXPLOTADORA": 3,
          "UTMX": 452540,
          "UTMY": 4597864,
          "LATITUD": 41.5292009102,
          "LONGITUD": 2.4299948328534,
          "ID_SUBZONA": null,
          "SUBZONA": null,
          "CONCESIONES": null
        },
        "ID_GRUPO": 1,
        "ID_LINEA": 47,
        "ID_TRAYECTO": 202,
        "SECUENCIA": 30,
        "ID_PARADA": 7216,
        "NKM_ORIGEN": 29.246,
        "SUBE_BAJA": 3
      }
    ],
    "COLOR": "#0BBC90",
    "numLinea": "47"
  },
  {
    "ID_GRUPO": 1,
    "ID_LINEA": 47,
    "ID_TRAYECTO": 5,
    "ID_TRAYECTO_SAE": 201,
    "DESC_TRAYECTO": "(E11.1) MATARÓ - CAMÍ RAL (RELLEU)",
    "DESC_REDUCIDA": "MAT-C.RAL(RELLEU)",
    "PRINCIPAL": "N",
    "SENTIDO": "I",
    "INI_TRAYECTO": 840,
    "FIN_TRAYECTO": 860,
    "ID_TRAYECTO_CONCAT": null,
    "TrayectosDet": [
      {
        "Parada": {
          "DESC_PARADA": "PL. DE LES TERESES",
          "COD_PARADA": 20,
          "ID_GRUPO": 1,
          "ID_PARADA": 7077,
          "ID_MUNICIPIO": 81213,
          "MUNICIPIO": "MATARÓ",
          "EXPLOTADORA": "CASAS",
          "ID_ZONA": 0,
          "ZONA": null,
          "ID_EXPLOTADORA": 3,
          "UTMX": 453574,
          "UTMY": 4598922,
          "LATITUD": 41.53885529546,
          "LONGITUD": 2.4423067153257,
          "ID_SUBZONA": null,
          "SUBZONA": null,
          "CONCESIONES": null
        },
        "ID_GRUPO": 1,
        "ID_LINEA": 47,
        "ID_TRAYECTO": 5,
        "SECUENCIA": 10,
        "ID_PARADA": 7077,
        "NKM_ORIGEN": 0,
        "SUBE_BAJA": 2
      },
      {
        "Parada": {
          "DESC_PARADA": "C. DE SANT ISIDOR",
          "COD_PARADA": 291,
          "ID_GRUPO": 1,
          "ID_PARADA": 13521,
          "ID_MUNICIPIO": 81213,
          "MUNICIPIO": "MATARÓ",
          "EXPLOTADORA": "CASAS",
          "ID_ZONA": 0,
          "ZONA": null,
          "ID_EXPLOTADORA": 3,
          "UTMX": 453396,
          "UTMY": 4599157,
          "LATITUD": 41.540897242805,
          "LONGITUD": 2.4401502037049,
          "ID_SUBZONA": null,
          "SUBZONA": null,
          "CONCESIONES": null
        },
        "ID_GRUPO": 1,
        "ID_LINEA": 47,
        "ID_TRAYECTO": 5,
        "SECUENCIA": 20,
        "ID_PARADA": 13521,
        "NKM_ORIGEN": 0.32,
        "SUBE_BAJA": 2
      },
      {
        "Parada": {
          "DESC_PARADA": "PL. D´ESPANYA (PARC CENTRAL)",
          "COD_PARADA": 3990,
          "ID_GRUPO": 1,
          "ID_PARADA": 7154,
          "ID_MUNICIPIO": 81213,
          "MUNICIPIO": "MATARÓ",
          "EXPLOTADORA": "CASAS",
          "ID_ZONA": 0,
          "ZONA": null,
          "ID_EXPLOTADORA": 3,
          "UTMX": 453525,
          "UTMY": 4599567,
          "LATITUD": 41.544597689691,
          "LONGITUD": 2.4416693344182,
          "ID_SUBZONA": null,
          "SUBZONA": null,
          "CONCESIONES": null
        },
        "ID_GRUPO": 1,
        "ID_LINEA": 47,
        "ID_TRAYECTO": 5,
        "SECUENCIA": 30,
        "ID_PARADA": 7154,
        "NKM_ORIGEN": 0.9,
        "SUBE_BAJA": 2
      },
      {
        "Parada": {
          "DESC_PARADA": "CAMÍ DE LA GEGANTA/PL. GRANOLLERS (POLICIA LOCAL)",
          "COD_PARADA": 7475,
          "ID_GRUPO": 1,
          "ID_PARADA": 21749,
          "ID_MUNICIPIO": 81213,
          "MUNICIPIO": "MATARÓ",
          "EXPLOTADORA": "CASAS",
          "ID_ZONA": 0,
          "ZONA": null,
          "ID_EXPLOTADORA": 3,
          "UTMX": 453090,
          "UTMY": 4599200,
          "LATITUD": 41.541266,
          "LONGITUD": 2.436482,
          "ID_SUBZONA": null,
          "SUBZONA": null,
          "CONCESIONES": null
        },
        "ID_GRUPO": 1,
        "ID_LINEA": 47,
        "ID_TRAYECTO": 5,
        "SECUENCIA": 45,
        "ID_PARADA": 21749,
        "NKM_ORIGEN": 2.28,
        "SUBE_BAJA": 2
      },
      {
        "Parada": {
          "DESC_PARADA": "RDA. DE LA REPÚBLICA / C. DE MIQUEL BIADA",
          "COD_PARADA": 30,
          "ID_GRUPO": 1,
          "ID_PARADA": 7048,
          "ID_MUNICIPIO": 81213,
          "MUNICIPIO": "MATARÓ",
          "EXPLOTADORA": "CASAS",
          "ID_ZONA": 0,
          "ZONA": null,
          "ID_EXPLOTADORA": 3,
          "UTMX": 453111,
          "UTMY": 4598733,
          "LATITUD": 41.537061683521,
          "LONGITUD": 2.4367710552247,
          "ID_SUBZONA": null,
          "SUBZONA": null,
          "CONCESIONES": null
        },
        "ID_GRUPO": 1,
        "ID_LINEA": 47,
        "ID_TRAYECTO": 5,
        "SECUENCIA": 50,
        "ID_PARADA": 7048,
        "NKM_ORIGEN": 2.84,
        "SUBE_BAJA": 2
      },
      {
        "Parada": {
          "DESC_PARADA": "CAMÍ RAL/C. PIZARRO (PL. DR. FLEMING)",
          "COD_PARADA": 11,
          "ID_GRUPO": 1,
          "ID_PARADA": 7159,
          "ID_MUNICIPIO": 81213,
          "MUNICIPIO": "MATARÓ",
          "EXPLOTADORA": "CASAS",
          "ID_ZONA": 0,
          "ZONA": null,
          "ID_EXPLOTADORA": 3,
          "UTMX": 453353,
          "UTMY": 4598354,
          "LATITUD": 41.533662215034,
          "LONGITUD": 2.4397015280912,
          "ID_SUBZONA": null,
          "SUBZONA": null,
          "CONCESIONES": null
        },
        "ID_GRUPO": 1,
        "ID_LINEA": 47,
        "ID_TRAYECTO": 5,
        "SECUENCIA": 60,
        "ID_PARADA": 7159,
        "NKM_ORIGEN": 3.34,
        "SUBE_BAJA": 2
      },
      {
        "Parada": {
          "DESC_PARADA": "CAMÍ RAL (PORTA LAIETANA-TECNOCAMPUS)",
          "COD_PARADA": 12,
          "ID_GRUPO": 1,
          "ID_PARADA": 7160,
          "ID_MUNICIPIO": 81213,
          "MUNICIPIO": "MATARÓ",
          "EXPLOTADORA": "CASAS",
          "ID_ZONA": 0,
          "ZONA": null,
          "ID_EXPLOTADORA": 3,
          "UTMX": 453028,
          "UTMY": 4597998,
          "LATITUD": 41.530436687756,
          "LONGITUD": 2.4358336078779,
          "ID_SUBZONA": null,
          "SUBZONA": null,
          "CONCESIONES": null
        },
        "ID_GRUPO": 1,
        "ID_LINEA": 47,
        "ID_TRAYECTO": 5,
        "SECUENCIA": 70,
        "ID_PARADA": 7160,
        "NKM_ORIGEN": 3.84,
        "SUBE_BAJA": 2
      }
    ],
    "COLOR": "#0BBC90",
    "numLinea": "47"
  },
  {
    "ID_GRUPO": 1,
    "ID_LINEA": 47,
    "ID_TRAYECTO": 6,
    "ID_TRAYECTO_SAE": 301,
    "DESC_TRAYECTO": "(E11.1) CAMÍ RAL - BARCELONA (RELLEU)",
    "DESC_REDUCIDA": "C.RAL-BARNA(RELLEU)",
    "PRINCIPAL": "N",
    "SENTIDO": "I",
    "INI_TRAYECTO": 860,
    "FIN_TRAYECTO": 920,
    "ID_TRAYECTO_CONCAT": null,
    "TrayectosDet": [
      {
        "Parada": {
          "DESC_PARADA": "CAMÍ RAL (PORTA LAIETANA-TECNOCAMPUS)",
          "COD_PARADA": 12,
          "ID_GRUPO": 1,
          "ID_PARADA": 7160,
          "ID_MUNICIPIO": 81213,
          "MUNICIPIO": "MATARÓ",
          "EXPLOTADORA": "CASAS",
          "ID_ZONA": 0,
          "ZONA": null,
          "ID_EXPLOTADORA": 3,
          "UTMX": 453028,
          "UTMY": 4597998,
          "LATITUD": 41.530436687756,
          "LONGITUD": 2.4358336078779,
          "ID_SUBZONA": null,
          "SUBZONA": null,
          "CONCESIONES": null
        },
        "ID_GRUPO": 1,
        "ID_LINEA": 47,
        "ID_TRAYECTO": 6,
        "SECUENCIA": 10,
        "ID_PARADA": 7160,
        "NKM_ORIGEN": 0,
        "SUBE_BAJA": 2
      },
      {
        "Parada": {
          "DESC_PARADA": "PL.TETUAN (GVCC /NÀPOLS)",
          "COD_PARADA": 13,
          "ID_GRUPO": 1,
          "ID_PARADA": 7506,
          "ID_MUNICIPIO": 439863,
          "MUNICIPIO": "BARCELONA",
          "EXPLOTADORA": "CASAS",
          "ID_ZONA": 0,
          "ZONA": null,
          "ID_EXPLOTADORA": 3,
          "UTMX": 431313,
          "UTMY": 4583281,
          "LATITUD": 41.39621,
          "LONGITUD": 2.17692,
          "ID_SUBZONA": null,
          "SUBZONA": null,
          "CONCESIONES": null
        },
        "ID_GRUPO": 1,
        "ID_LINEA": 47,
        "ID_TRAYECTO": 6,
        "SECUENCIA": 20,
        "ID_PARADA": 7506,
        "NKM_ORIGEN": 28,
        "SUBE_BAJA": 3
      },
      {
        "Parada": {
          "DESC_PARADA": "RONDA DE LA UNIVERSITAT 25",
          "COD_PARADA": 6190,
          "ID_GRUPO": 1,
          "ID_PARADA": 7022,
          "ID_MUNICIPIO": 439863,
          "MUNICIPIO": "BARCELONA",
          "EXPLOTADORA": "CASAS",
          "ID_ZONA": 0,
          "ZONA": null,
          "ID_EXPLOTADORA": 3,
          "UTMX": 430638,
          "UTMY": 4582238,
          "LATITUD": 41.38689,
          "LONGITUD": 2.166885,
          "ID_SUBZONA": null,
          "SUBZONA": null,
          "CONCESIONES": null
        },
        "ID_GRUPO": 1,
        "ID_LINEA": 47,
        "ID_TRAYECTO": 6,
        "SECUENCIA": 30,
        "ID_PARADA": 7022,
        "NKM_ORIGEN": 29.96,
        "SUBE_BAJA": 3
      }
    ],
    "COLOR": "#0BBC90",
    "numLinea": "47"
  }
]